LICENSE
pyvizbee/__init__.py
pyvizbee/__main__.py
pyvizbee/add_path.py
pyvizbee/align_df_sliced.py
pyvizbee/align_ns_df.py
pyvizbee/align_sents.py
pyvizbee/amend_avec.py
pyvizbee/cb_save_tsv.py
pyvizbee/cb_save_xlsx.py
pyvizbee/cb_sent_align.py
pyvizbee/cb_show_nsdf.py
pyvizbee/color_map.py
pyvizbee/display_text_widget.py-
pyvizbee/filevalue2list.py
pyvizbee/gen_df.py
pyvizbee/gen_pairs.py
pyvizbee/load_text_widget.py-
pyvizbee/loadtext.py
pyvizbee/locate_index_pairs.py
pyvizbee/loglevel.py
pyvizbee/model_test_zh.lzma
pyvizbee/not_docked_indices.py
pyvizbee/ns.py
pyvizbee/seg_text_fix.py
pyvizbee/sent_align_df_sliced.py
pyvizbee/sent_align_ns_df.py
pyvizbee/template.py
pyvizbee/template.py-
pyvizbee/test-en.txt
pyvizbee/test-zh.txt
pyvizbee-0.1.0a4.dist-info/LICENSE
pyvizbee-0.1.0a4.dist-info/WHEEL
pyvizbee-0.1.0a4.dist-info/METADATA
pyvizbee-0.1.0a4.dist-info/RECORD
